LICENSE.txt
iuguclient/__init__.py
iuguclient/action.py
iuguclient/customer.py
iuguclient/exception.py
iuguclient/invoice.py
iuguclient/iuguapi.py
iuguclient/marketplace.py
iuguclient/plan.py
iuguclient/subscription.py
iuguclient/token.py
iuguclient/transfer.py
iuguclient/version.py
iuguclient-0.1.5.dist-info/LICENSE.txt
iuguclient-0.1.5.dist-info/WHEEL
iuguclient-0.1.5.dist-info/METADATA
iuguclient-0.1.5.dist-info/RECORD
