Metadata-Version: 2.1
Name: iuguclient
Version: 0.1.5
Summary: 
Home-page: https://github.com/erickod/iugu-client
License: MIT
Author: Erick Duarte
Author-email: erickod@gmail.com
Requires-Python: >=3.7,<4.0
Classifier: License :: OSI Approved :: MIT License
Classifier: Programming Language :: Python :: 3
Classifier: Programming Language :: Python :: 3.10
Classifier: Programming Language :: Python :: 3.7
Classifier: Programming Language :: Python :: 3.8
Classifier: Programming Language :: Python :: 3.9
Requires-Dist: requests (>=2.27.1,<3.0.0)
Project-URL: Repository, https://github.com/erickod/iugu-client
